voluxcontroller/__init__.py
voluxcontroller/__version__.py
voluxcontroller-0.1.0a2.dist-info/METADATA
voluxcontroller-0.1.0a2.dist-info/WHEEL
voluxcontroller-0.1.0a2.dist-info/RECORD
